{
 "custom_fields": [
  {
   "_assign": null,
   "_comments": null,
   "_liked_by": null,
   "_user_tags": null,
   "allow_in_quick_entry": 0,
   "allow_on_submit": 0,
   "bold": 0,
   "collapsible": 1,
   "collapsible_depends_on": null,
   "columns": 0,
   "creation": "2022-08-23 07:07:34.801856",
   "default": null,
   "depends_on": null,
   "description": null,
   "docstatus": 0,
   "dt": "Payment Entry",
   "fetch_from": null,
   "fetch_if_empty": 0,
   "fieldname": "additional_discount",
   "fieldtype": "Section Break",
   "hidden": 0,
   "hide_border": 0,
   "hide_days": 0,
   "hide_seconds": 0,
   "idx": 44,
   "ignore_user_permissions": 0,
   "ignore_xss_filter": 0,
   "in_global_search": 0,
   "in_list_view": 0,
   "in_preview": 0,
   "in_standard_filter": 0,
   "insert_after": "references",
   "label": "Additional Discount",
   "length": 0,
   "mandatory_depends_on": null,
   "modified": "2022-08-23 07:07:34.801856",
   "modified_by": "Administrator",
   "name": "Payment Entry-additional_discount",
   "no_copy": 0,
   "non_negative": 0,
   "options": null,
   "owner": "Administrator",
   "parent": null,
   "parentfield": null,
   "parenttype": null,
   "permlevel": 0,
   "precision": "",
   "print_hide": 0,
   "print_hide_if_no_value": 0,
   "print_width": null,
   "read_only": 0,
   "read_only_depends_on": null,
   "report_hide": 0,
   "reqd": 0,
   "search_index": 0,
   "translatable": 0,
   "unique": 0,
   "width": null
  },
  {
   "_assign": null,
   "_comments": null,
   "_liked_by": null,
   "_user_tags": null,
   "allow_in_quick_entry": 0,
   "allow_on_submit": 0,
   "bold": 0,
   "collapsible": 0,
   "collapsible_depends_on": null,
   "columns": 0,
   "creation": "2022-08-23 07:07:36.113412",
   "default": null,
   "depends_on": null,
   "description": null,
   "docstatus": 0,
   "dt": "Payment Entry",
   "fetch_from": null,
   "fetch_if_empty": 0,
   "fieldname": "additional_discount_account",
   "fieldtype": "Link",
   "hidden": 0,
   "hide_border": 0,
   "hide_days": 0,
   "hide_seconds": 0,
   "idx": 44,
   "ignore_user_permissions": 0,
   "ignore_xss_filter": 0,
   "in_global_search": 0,
   "in_list_view": 0,
   "in_preview": 0,
   "in_standard_filter": 0,
   "insert_after": "additional_discount",
   "label": "Additional Discount Account",
   "length": 0,
   "mandatory_depends_on": "additional_discount_amount",
   "modified": "2022-08-23 07:07:36.113412",
   "modified_by": "Administrator",
   "name": "Payment Entry-additional_discount_account",
   "no_copy": 0,
   "non_negative": 0,
   "options": "Account",
   "owner": "Administrator",
   "parent": null,
   "parentfield": null,
   "parenttype": null,
   "permlevel": 0,
   "precision": "",
   "print_hide": 0,
   "print_hide_if_no_value": 0,
   "print_width": null,
   "read_only": 0,
   "read_only_depends_on": null,
   "report_hide": 0,
   "reqd": 0,
   "search_index": 0,
   "translatable": 0,
   "unique": 0,
   "width": null
  },
  {
   "_assign": null,
   "_comments": null,
   "_liked_by": null,
   "_user_tags": null,
   "allow_in_quick_entry": 0,
   "allow_on_submit": 0,
   "bold": 0,
   "collapsible": 0,
   "collapsible_depends_on": null,
   "columns": 0,
   "creation": "2022-08-23 07:07:36.921143",
   "default": null,
   "depends_on": null,
   "description": null,
   "docstatus": 0,
   "dt": "Payment Entry",
   "fetch_from": null,
   "fetch_if_empty": 0,
   "fieldname": "column_break_46",
   "fieldtype": "Column Break",
   "hidden": 0,
   "hide_border": 0,
   "hide_days": 0,
   "hide_seconds": 0,
   "idx": 46,
   "ignore_user_permissions": 0,
   "ignore_xss_filter": 0,
   "in_global_search": 0,
   "in_list_view": 0,
   "in_preview": 0,
   "in_standard_filter": 0,
   "insert_after": "additional_discount_account",
   "label": null,
   "length": 0,
   "mandatory_depends_on": null,
   "modified": "2022-08-23 07:07:36.921143",
   "modified_by": "Administrator",
   "name": "Payment Entry-column_break_46",
   "no_copy": 0,
   "non_negative": 0,
   "options": null,
   "owner": "Administrator",
   "parent": null,
   "parentfield": null,
   "parenttype": null,
   "permlevel": 0,
   "precision": "",
   "print_hide": 0,
   "print_hide_if_no_value": 0,
   "print_width": null,
   "read_only": 0,
   "read_only_depends_on": null,
   "report_hide": 0,
   "reqd": 0,
   "search_index": 0,
   "translatable": 0,
   "unique": 0,
   "width": null
  },
  {
   "_assign": null,
   "_comments": null,
   "_liked_by": null,
   "_user_tags": null,
   "allow_in_quick_entry": 0,
   "allow_on_submit": 0,
   "bold": 0,
   "collapsible": 0,
   "collapsible_depends_on": null,
   "columns": 0,
   "creation": "2022-08-23 07:15:25.697048",
   "default": null,
   "depends_on": null,
   "description": null,
   "docstatus": 0,
   "dt": "Payment Entry",
   "fetch_from": null,
   "fetch_if_empty": 0,
   "fieldname": "additional_discount_amount",
   "fieldtype": "Currency",
   "hidden": 0,
   "hide_border": 0,
   "hide_days": 0,
   "hide_seconds": 0,
   "idx": 47,
   "ignore_user_permissions": 0,
   "ignore_xss_filter": 0,
   "in_global_search": 0,
   "in_list_view": 0,
   "in_preview": 0,
   "in_standard_filter": 0,
   "insert_after": "column_break_46",
   "label": "Additional Discount Amount",
   "length": 0,
   "mandatory_depends_on": null,
   "modified": "2022-08-23 07:15:25.697048",
   "modified_by": "Administrator",
   "name": "Payment Entry-additional_discount_amount",
   "no_copy": 0,
   "non_negative": 0,
   "options": null,
   "owner": "Administrator",
   "parent": null,
   "parentfield": null,
   "parenttype": null,
   "permlevel": 0,
   "precision": "",
   "print_hide": 0,
   "print_hide_if_no_value": 0,
   "print_width": null,
   "read_only": 0,
   "read_only_depends_on": null,
   "report_hide": 0,
   "reqd": 0,
   "search_index": 0,
   "translatable": 0,
   "unique": 0,
   "width": null
  }
 ],
 "custom_perms": [],
 "doctype": "Payment Entry",
 "property_setters": [],
 "sync_on_migrate": 1
}